s3_compress/__init__.py
s3_compress/zipping_s3.py
s3_simple_compress-0.1.1.dist-info/LICENSE
s3_simple_compress-0.1.1.dist-info/METADATA
s3_simple_compress-0.1.1.dist-info/WHEEL
s3_simple_compress-0.1.1.dist-info/RECORD
