Metadata-Version: 2.1
Name: s3-simple-compress
Version: 0.1.1
Summary: Documentation for AWS S3 In-Memory File Compression (zip) Program 
License: MIT
Author: Bruno Mesquita
Author-email: bruno.mesquita2707@gmail.com
Requires-Python: >=3.11,<4.0
Classifier: Development Status :: 4 - Beta
Classifier: Environment :: Web Environment
Classifier: Framework :: AWS CDK
Classifier: Intended Audience :: Developers
Classifier: Intended Audience :: Information Technology
Classifier: Intended Audience :: System Administrators
Classifier: License :: OSI Approved :: MIT License
Classifier: Natural Language :: English
Classifier: Operating System :: OS Independent
Classifier: Programming Language :: Python
Classifier: Programming Language :: Python :: 3
Classifier: Programming Language :: Python :: 3.11
Classifier: Programming Language :: Python :: 3
Classifier: Programming Language :: Python :: 3.11
Classifier: Topic :: Education :: Testing
Classifier: Topic :: Internet
Classifier: Topic :: Software Development
Classifier: Topic :: Software Development :: Libraries
Classifier: Topic :: Software Development :: Libraries :: Python Modules
Requires-Dist: boto3 (>=1.25.0,<1.26.98)
Requires-Dist: ipywidgets (>=8.0.6,<9.0.0)
Requires-Dist: rich (>=13.3.5,<14.0.0)
Project-URL: Bug Tracker, https://github.com/BrunoMesquitaa/s3_simple_compress/issues
Project-URL: Código, https://github.com/BrunoMesquitaa/s3_simple_compress
Project-URL: Documentação, https://s3-simple-compress.readthedocs.io/en/latest/
